hypella/__init__.py
hypella/cli.py
hypella-0.0.1.dist-info/METADATA
hypella-0.0.1.dist-info/WHEEL
hypella-0.0.1.dist-info/entry_points.txt
hypella-0.0.1.dist-info/licenses/LICENSE
hypella-0.0.1.dist-info/RECORD
